{"videoId": "_UwnXZUoNAs", "contour": [{"tMs": 115, "midi": 38.7}, {"tMs": 138, "midi": 38.7}, {"tMs": 161, "midi": 39.2}, {"tMs": 184, "midi": 39.2}, {"tMs": 207, "midi": 39.2}, {"tMs": 230, "midi": 39.2}, {"tMs": 253, "midi": 39.2}, {"tMs": 276, "midi": 39.2}, {"tMs": 299, "midi": 38.7}, {"tMs": 322, "midi": 38.7}, {"tMs": 345, "midi": 38.7}, {"tMs": 368, "midi": 38.7}, {"tMs": 391, "midi": 38.7}, {"tMs": 414, "midi": 38.7}, {"tMs": 437, "midi": 38.7}, {"tMs": 460, "midi": 38.7}, {"tMs": 552, "midi": 38.7}, {"tMs": 575, "midi": 38.7}, {"tMs": 598, "midi": 39.2}, {"tMs": 621, "midi": 40.8}, {"tMs": 644, "midi": 40.8}, {"tMs": 667, "midi": 40.8}, {"tMs": 690, "midi": 40.8}, {"tMs": 713, "midi": 40.8}, {"tMs": 736, "midi": 40.8}, {"tMs": 782, "midi": 48.1}, {"tMs": 805, "midi": 48.1}, {"tMs": 828, "midi": 48.1}, {"tMs": 851, "midi": 48.9}, {"tMs": 874, "midi": 48.9}, {"tMs": 897, "midi": 48.9}, {"tMs": 920, "midi": 48.1}, {"tMs": 943, "midi": 48.1}, {"tMs": 966, "midi": 48.1}, {"tMs": 989, "midi": 48.1}, {"tMs": 1012, "midi": 48.9}, {"tMs": 1035, "midi": 48.9}, {"tMs": 1058, "midi": 48.9}, {"tMs": 1081, "midi": 48.9}, {"tMs": 1104, "midi": 48.9}, {"tMs": 1127, "midi": 47.2}, {"tMs": 1150, "midi": 47.2}, {"tMs": 1173, "midi": 47.2}, {"tMs": 1196, "midi": 47.2}, {"tMs": 1219, "midi": 47.2}, {"tMs": 1242, "midi": 47.2}, {"tMs": 1265, "midi": 47.2}, {"tMs": 1288, "midi": 45.8}, {"tMs": 1311, "midi": 45.7}, {"tMs": 1334, "midi": 47.2}, {"tMs": 1357, "midi": 45.8}, {"tMs": 1380, "midi": 45.8}, {"tMs": 1403, "midi": 40.8}, {"tMs": 1426, "midi": 40.8}, {"tMs": 1449, "midi": 40.8}, {"tMs": 1472, "midi": 40.8}, {"tMs": 1495, "midi": 40.8}, {"tMs": 1518, "midi": 40.8}, {"tMs": 1541, "midi": 40.8}, {"tMs": 1564, "midi": 40.8}, {"tMs": 1587, "midi": 40.8}, {"tMs": 1610, "midi": 40.8}, {"tMs": 1633, "midi": 40.8}, {"tMs": 1656, "midi": 40.8}, {"tMs": 1679, "midi": 40.8}, {"tMs": 1702, "midi": 41.9}, {"tMs": 1725, "midi": 43.1}, {"tMs": 1748, "midi": 43.1}, {"tMs": 1771, "midi": 43.1}, {"tMs": 1794, "midi": 43.1}, {"tMs": 1817, "midi": 43.1}, {"tMs": 1840, "midi": 43.1}, {"tMs": 1886, "midi": 40.8}, {"tMs": 1909, "midi": 40.8}, {"tMs": 1932, "midi": 40.8}, {"tMs": 1955, "midi": 40.8}, {"tMs": 1978, "midi": 40.8}, {"tMs": 2001, "midi": 40.8}, {"tMs": 2024, "midi": 40.8}, {"tMs": 2047, "midi": 40.8}, {"tMs": 2070, "midi": 40.8}, {"tMs": 2093, "midi": 40.8}, {"tMs": 2116, "midi": 40.8}, {"tMs": 2139, "midi": 40.8}, {"tMs": 2162, "midi": 40.8}, {"tMs": 2185, "midi": 40.8}, {"tMs": 2208, "midi": 45.7}, {"tMs": 2231, "midi": 45.7}, {"tMs": 2254, "midi": 45.7}, {"tMs": 2277, "midi": 45.7}, {"tMs": 2300, "midi": 45.7}, {"tMs": 2323, "midi": 45.7}, {"tMs": 2346, "midi": 45.8}, {"tMs": 2369, "midi": 45.8}, {"tMs": 2392, "midi": 45.8}, {"tMs": 2415, "midi": 47.3}, {"tMs": 2438, "midi": 47.2}, {"tMs": 2461, "midi": 47.2}, {"tMs": 2484, "midi": 47.2}, {"tMs": 2507, "midi": 47.2}, {"tMs": 2530, "midi": 47.2}, {"tMs": 2553, "midi": 47.2}, {"tMs": 2576, "midi": 47.2}, {"tMs": 2599, "midi": 47.2}, {"tMs": 2622, "midi": 47.2}, {"tMs": 2668, "midi": 40.8}, {"tMs": 2691, "midi": 40.2}, {"tMs": 2714, "midi": 40.2}, {"tMs": 2737, "midi": 40.8}, {"tMs": 2760, "midi": 40.2}, {"tMs": 2783, "midi": 40.8}, {"tMs": 2806, "midi": 40.8}, {"tMs": 2829, "midi": 40.8}, {"tMs": 2852, "midi": 40.8}, {"tMs": 2875, "midi": 39.7}, {"tMs": 2898, "midi": 39.2}, {"tMs": 2921, "midi": 39.2}, {"tMs": 2944, "midi": 39.2}, {"tMs": 2967, "midi": 38.7}, {"tMs": 2990, "midi": 38.7}, {"tMs": 3013, "midi": 38.7}, {"tMs": 3036, "midi": 38.7}, {"tMs": 3059, "midi": 38.7}, {"tMs": 3082, "midi": 38.7}, {"tMs": 3105, "midi": 38.7}, {"tMs": 3151, "midi": 40.8}, {"tMs": 3174, "midi": 40.8}, {"tMs": 3197, "midi": 40.8}, {"tMs": 3220, "midi": 40.8}, {"tMs": 3243, "midi": 40.8}, {"tMs": 3266, "midi": 40.8}, {"tMs": 3289, "midi": 40.8}, {"tMs": 3335, "midi": 48.9}, {"tMs": 3358, "midi": 48.9}, {"tMs": 3381, "midi": 48.9}, {"tMs": 3404, "midi": 48.9}, {"tMs": 3427, "midi": 48.9}, {"tMs": 3450, "midi": 48.9}, {"tMs": 3473, "midi": 48.9}, {"tMs": 3496, "midi": 48.9}, {"tMs": 3519, "midi": 48.1}, {"tMs": 3542, "midi": 48.1}, {"tMs": 3565, "midi": 48.1}, {"tMs": 3588, "midi": 48.1}, {"tMs": 3611, "midi": 48.0}, {"tMs": 3634, "midi": 47.2}, {"tMs": 3657, "midi": 47.2}, {"tMs": 3680, "midi": 47.2}, {"tMs": 3703, "midi": 47.2}, {"tMs": 3726, "midi": 47.2}, {"tMs": 3749, "midi": 47.2}, {"tMs": 3772, "midi": 47.1}, {"tMs": 3795, "midi": 47.0}, {"tMs": 3818, "midi": 46.6}, {"tMs": 3841, "midi": 46.5}, {"tMs": 3864, "midi": 46.5}, {"tMs": 3887, "midi": 47.2}, {"tMs": 3910, "midi": 47.3}, {"tMs": 3956, "midi": 41.3}, {"tMs": 3979, "midi": 41.3}, {"tMs": 4002, "midi": 41.3}, {"tMs": 4025, "midi": 41.3}, {"tMs": 4048, "midi": 41.3}, {"tMs": 4071, "midi": 41.3}, {"tMs": 4094, "midi": 40.8}, {"tMs": 4117, "midi": 40.8}, {"tMs": 4140, "midi": 40.8}, {"tMs": 4163, "midi": 40.8}, {"tMs": 4186, "midi": 40.8}, {"tMs": 4209, "midi": 40.8}, {"tMs": 4232, "midi": 40.8}, {"tMs": 4255, "midi": 40.8}, {"tMs": 4278, "midi": 40.8}, {"tMs": 4301, "midi": 40.8}, {"tMs": 4324, "midi": 36.9}, {"tMs": 4439, "midi": 40.8}, {"tMs": 4462, "midi": 40.8}, {"tMs": 4485, "midi": 40.8}, {"tMs": 4508, "midi": 40.8}, {"tMs": 4531, "midi": 40.8}, {"tMs": 4554, "midi": 40.8}, {"tMs": 4577, "midi": 40.8}, {"tMs": 4600, "midi": 40.8}, {"tMs": 4623, "midi": 40.8}, {"tMs": 4646, "midi": 40.8}, {"tMs": 4669, "midi": 40.8}, {"tMs": 4692, "midi": 41.3}, {"tMs": 4715, "midi": 41.3}, {"tMs": 4738, "midi": 40.8}, {"tMs": 4761, "midi": 40.8}, {"tMs": 4784, "midi": 45.0}, {"tMs": 4807, "midi": 45.0}, {"tMs": 4830, "midi": 45.0}, {"tMs": 4853, "midi": 45.0}, {"tMs": 4968, "midi": 65.0}, {"tMs": 4991, "midi": 65.0}, {"tMs": 5014, "midi": 66.6}, {"tMs": 5037, "midi": 66.6}, {"tMs": 5060, "midi": 66.4}, {"tMs": 5083, "midi": 65.0}, {"tMs": 5106, "midi": 65.1}, {"tMs": 5129, "midi": 65.1}, {"tMs": 5152, "midi": 65.1}, {"tMs": 5175, "midi": 66.1}, {"tMs": 5658, "midi": 70.9}, {"tMs": 5681, "midi": 70.5}, {"tMs": 5704, "midi": 72.1}, {"tMs": 5727, "midi": 71.7}, {"tMs": 5750, "midi": 71.3}, {"tMs": 5773, "midi": 70.8}, {"tMs": 5796, "midi": 70.8}, {"tMs": 5819, "midi": 70.8}, {"tMs": 5842, "midi": 70.8}, {"tMs": 5865, "midi": 70.6}, {"tMs": 5888, "midi": 72.1}, {"tMs": 5911, "midi": 72.7}, {"tMs": 5934, "midi": 72.8}, {"tMs": 5957, "midi": 72.8}, {"tMs": 5980, "midi": 72.8}, {"tMs": 6003, "midi": 72.8}, {"tMs": 6187, "midi": 48.9}, {"tMs": 6210, "midi": 48.8}, {"tMs": 6233, "midi": 47.2}, {"tMs": 6256, "midi": 47.2}, {"tMs": 6279, "midi": 47.2}, {"tMs": 6302, "midi": 47.2}, {"tMs": 6325, "midi": 47.2}, {"tMs": 6348, "midi": 46.5}, {"tMs": 6371, "midi": 46.5}, {"tMs": 6394, "midi": 46.5}, {"tMs": 6417, "midi": 46.5}, {"tMs": 6440, "midi": 47.2}, {"tMs": 6463, "midi": 47.2}, {"tMs": 6486, "midi": 46.8}, {"tMs": 6509, "midi": 46.8}, {"tMs": 6555, "midi": 41.3}, {"tMs": 6578, "midi": 41.3}, {"tMs": 6601, "midi": 41.0}, {"tMs": 6624, "midi": 41.0}, {"tMs": 6647, "midi": 41.0}, {"tMs": 6670, "midi": 41.0}, {"tMs": 6693, "midi": 40.9}, {"tMs": 6716, "midi": 41.0}, {"tMs": 6739, "midi": 40.8}, {"tMs": 6762, "midi": 40.8}, {"tMs": 6785, "midi": 40.8}, {"tMs": 6808, "midi": 41.0}, {"tMs": 6831, "midi": 41.1}, {"tMs": 6854, "midi": 41.1}, {"tMs": 6877, "midi": 41.1}, {"tMs": 6900, "midi": 41.1}, {"tMs": 6923, "midi": 41.1}, {"tMs": 6946, "midi": 39.1}, {"tMs": 7038, "midi": 41.1}, {"tMs": 7061, "midi": 41.1}, {"tMs": 7084, "midi": 41.1}, {"tMs": 7107, "midi": 41.0}, {"tMs": 7130, "midi": 41.1}, {"tMs": 7153, "midi": 41.0}, {"tMs": 7176, "midi": 41.1}, {"tMs": 7199, "midi": 41.1}, {"tMs": 7222, "midi": 41.1}, {"tMs": 7245, "midi": 41.1}, {"tMs": 7268, "midi": 41.1}, {"tMs": 7291, "midi": 41.0}, {"tMs": 7314, "midi": 41.3}, {"tMs": 7337, "midi": 45.1}, {"tMs": 7360, "midi": 45.1}, {"tMs": 7383, "midi": 45.1}, {"tMs": 7406, "midi": 45.1}, {"tMs": 7429, "midi": 45.1}, {"tMs": 7452, "midi": 45.8}, {"tMs": 7521, "midi": 47.1}, {"tMs": 7544, "midi": 47.1}, {"tMs": 7567, "midi": 47.1}, {"tMs": 7590, "midi": 47.1}, {"tMs": 7613, "midi": 47.1}, {"tMs": 7636, "midi": 46.8}, {"tMs": 7659, "midi": 46.8}, {"tMs": 7682, "midi": 46.8}, {"tMs": 7705, "midi": 46.8}, {"tMs": 7728, "midi": 46.8}, {"tMs": 7751, "midi": 46.9}, {"tMs": 7797, "midi": 40.0}, {"tMs": 7820, "midi": 40.0}, {"tMs": 7843, "midi": 40.0}, {"tMs": 7866, "midi": 40.0}, {"tMs": 7889, "midi": 40.0}, {"tMs": 7912, "midi": 40.0}, {"tMs": 7935, "midi": 39.9}, {"tMs": 7958, "midi": 39.8}, {"tMs": 7981, "midi": 39.7}, {"tMs": 8004, "midi": 39.7}, {"tMs": 8027, "midi": 39.7}, {"tMs": 8050, "midi": 39.8}, {"tMs": 8073, "midi": 40.2}, {"tMs": 8096, "midi": 39.8}, {"tMs": 8119, "midi": 40.4}, {"tMs": 8142, "midi": 40.4}, {"tMs": 8165, "midi": 40.5}, {"tMs": 8280, "midi": 58.9}, {"tMs": 8303, "midi": 58.9}, {"tMs": 8326, "midi": 58.9}, {"tMs": 8349, "midi": 58.9}, {"tMs": 8372, "midi": 58.9}, {"tMs": 8395, "midi": 58.9}, {"tMs": 8418, "midi": 58.9}, {"tMs": 8441, "midi": 58.9}, {"tMs": 8464, "midi": 58.9}, {"tMs": 8487, "midi": 58.9}, {"tMs": 8510, "midi": 58.9}, {"tMs": 8533, "midi": 58.9}, {"tMs": 8556, "midi": 58.9}, {"tMs": 8579, "midi": 58.9}, {"tMs": 8602, "midi": 58.9}, {"tMs": 8625, "midi": 58.9}, {"tMs": 8648, "midi": 58.9}, {"tMs": 8671, "midi": 58.9}, {"tMs": 8694, "midi": 58.9}, {"tMs": 8717, "midi": 58.9}, {"tMs": 8740, "midi": 58.9}, {"tMs": 8763, "midi": 58.9}, {"tMs": 8786, "midi": 58.9}, {"tMs": 8809, "midi": 58.9}, {"tMs": 8832, "midi": 58.9}, {"tMs": 8855, "midi": 58.9}, {"tMs": 8878, "midi": 58.9}, {"tMs": 8901, "midi": 58.9}, {"tMs": 8924, "midi": 58.9}, {"tMs": 8947, "midi": 58.9}, {"tMs": 8970, "midi": 58.9}, {"tMs": 8993, "midi": 58.9}, {"tMs": 9016, "midi": 58.9}, {"tMs": 9039, "midi": 58.9}, {"tMs": 9062, "midi": 58.9}, {"tMs": 9085, "midi": 58.9}, {"tMs": 9108, "midi": 58.9}, {"tMs": 9131, "midi": 58.9}, {"tMs": 9154, "midi": 58.9}, {"tMs": 9177, "midi": 58.9}, {"tMs": 9200, "midi": 58.9}, {"tMs": 9223, "midi": 58.9}, {"tMs": 9246, "midi": 58.9}, {"tMs": 9269, "midi": 58.9}, {"tMs": 9292, "midi": 58.9}, {"tMs": 9315, "midi": 58.9}, {"tMs": 9338, "midi": 58.9}, {"tMs": 9361, "midi": 58.9}, {"tMs": 9384, "midi": 58.9}, {"tMs": 9407, "midi": 58.9}, {"tMs": 9430, "midi": 58.9}, {"tMs": 9453, "midi": 58.9}, {"tMs": 9476, "midi": 58.9}, {"tMs": 9499, "midi": 58.9}, {"tMs": 9522, "midi": 58.9}, {"tMs": 9545, "midi": 58.9}, {"tMs": 9568, "midi": 58.9}, {"tMs": 9591, "midi": 58.9}, {"tMs": 9614, "midi": 58.9}, {"tMs": 9637, "midi": 58.9}, {"tMs": 9660, "midi": 58.9}, {"tMs": 9683, "midi": 58.9}, {"tMs": 9706, "midi": 58.9}, {"tMs": 9729, "midi": 58.9}, {"tMs": 9752, "midi": 58.9}, {"tMs": 9775, "midi": 58.9}, {"tMs": 9798, "midi": 58.9}, {"tMs": 9821, "midi": 58.9}, {"tMs": 9844, "midi": 58.9}, {"tMs": 9867, "midi": 58.9}, {"tMs": 9890, "midi": 58.9}, {"tMs": 9913, "midi": 58.9}, {"tMs": 9936, "midi": 58.9}, {"tMs": 9959, "midi": 58.9}, {"tMs": 9982, "midi": 58.9}, {"tMs": 10005, "midi": 58.9}, {"tMs": 10028, "midi": 58.9}, {"tMs": 10051, "midi": 58.9}, {"tMs": 10074, "midi": 58.9}, {"tMs": 10097, "midi": 58.9}, {"tMs": 10120, "midi": 58.9}, {"tMs": 10143, "midi": 58.9}, {"tMs": 10166, "midi": 58.9}, {"tMs": 10189, "midi": 58.9}, {"tMs": 10212, "midi": 58.9}, {"tMs": 10350, "midi": 39.7}, {"tMs": 10373, "midi": 39.7}, {"tMs": 10396, "midi": 39.7}, {"tMs": 10419, "midi": 39.7}, {"tMs": 10442, "midi": 39.7}, {"tMs": 10465, "midi": 39.7}, {"tMs": 10488, "midi": 39.7}, {"tMs": 10511, "midi": 39.7}, {"tMs": 10534, "midi": 39.7}, {"tMs": 10557, "midi": 38.7}, {"tMs": 10580, "midi": 38.7}, {"tMs": 10603, "midi": 38.7}, {"tMs": 10626, "midi": 39.7}, {"tMs": 10649, "midi": 39.7}, {"tMs": 10672, "midi": 39.7}, {"tMs": 10695, "midi": 39.7}, {"tMs": 10718, "midi": 40.5}, {"tMs": 10741, "midi": 40.5}, {"tMs": 10764, "midi": 39.8}, {"tMs": 11109, "midi": 48.0}, {"tMs": 11132, "midi": 48.0}, {"tMs": 11155, "midi": 47.7}, {"tMs": 11178, "midi": 47.3}, {"tMs": 11201, "midi": 47.3}, {"tMs": 11224, "midi": 47.2}, {"tMs": 11247, "midi": 47.6}, {"tMs": 11270, "midi": 46.9}, {"tMs": 11293, "midi": 46.9}, {"tMs": 11316, "midi": 46.9}, {"tMs": 11339, "midi": 46.9}, {"tMs": 11362, "midi": 46.9}, {"tMs": 11385, "midi": 46.8}, {"tMs": 11408, "midi": 46.8}, {"tMs": 11431, "midi": 46.8}, {"tMs": 11454, "midi": 46.8}, {"tMs": 11477, "midi": 46.8}, {"tMs": 11500, "midi": 46.8}, {"tMs": 11523, "midi": 46.6}, {"tMs": 11546, "midi": 46.5}, {"tMs": 11569, "midi": 46.6}, {"tMs": 11592, "midi": 47.9}, {"tMs": 11661, "midi": 60.0}, {"tMs": 11684, "midi": 60.0}, {"tMs": 11707, "midi": 60.0}, {"tMs": 11730, "midi": 60.1}, {"tMs": 11753, "midi": 60.1}, {"tMs": 11776, "midi": 60.1}, {"tMs": 11799, "midi": 59.9}, {"tMs": 11822, "midi": 59.9}, {"tMs": 11845, "midi": 59.9}, {"tMs": 11868, "midi": 59.9}, {"tMs": 11891, "midi": 60.0}, {"tMs": 12098, "midi": 59.9}, {"tMs": 12121, "midi": 59.9}, {"tMs": 12144, "midi": 60.0}, {"tMs": 12167, "midi": 60.0}, {"tMs": 12190, "midi": 60.0}, {"tMs": 12213, "midi": 60.2}, {"tMs": 12236, "midi": 59.9}, {"tMs": 12259, "midi": 60.0}, {"tMs": 12282, "midi": 61.4}, {"tMs": 12305, "midi": 61.5}, {"tMs": 12328, "midi": 61.5}, {"tMs": 12351, "midi": 61.5}, {"tMs": 12374, "midi": 61.1}, {"tMs": 12397, "midi": 61.0}, {"tMs": 12420, "midi": 60.7}, {"tMs": 12443, "midi": 60.7}, {"tMs": 12466, "midi": 60.8}, {"tMs": 12489, "midi": 61.3}, {"tMs": 12512, "midi": 62.2}, {"tMs": 12535, "midi": 62.9}, {"tMs": 12558, "midi": 63.4}, {"tMs": 12581, "midi": 63.6}, {"tMs": 12880, "midi": 39.3}, {"tMs": 12903, "midi": 39.7}, {"tMs": 12926, "midi": 39.7}, {"tMs": 12949, "midi": 39.7}, {"tMs": 12972, "midi": 39.7}, {"tMs": 12995, "midi": 39.7}, {"tMs": 13018, "midi": 39.7}, {"tMs": 13041, "midi": 39.7}, {"tMs": 13064, "midi": 39.7}, {"tMs": 13087, "midi": 39.7}, {"tMs": 13110, "midi": 39.7}, {"tMs": 13133, "midi": 39.7}, {"tMs": 13156, "midi": 39.9}, {"tMs": 13179, "midi": 39.9}, {"tMs": 13202, "midi": 40.7}, {"tMs": 13225, "midi": 40.7}, {"tMs": 13248, "midi": 40.7}, {"tMs": 13271, "midi": 40.7}, {"tMs": 13294, "midi": 40.7}, {"tMs": 13317, "midi": 39.2}, {"tMs": 13616, "midi": 36.2}, {"tMs": 13639, "midi": 37.0}, {"tMs": 13662, "midi": 36.5}, {"tMs": 13685, "midi": 36.0}, {"tMs": 13708, "midi": 36.0}, {"tMs": 13731, "midi": 36.0}, {"tMs": 13754, "midi": 36.0}, {"tMs": 13777, "midi": 36.0}, {"tMs": 14168, "midi": 41.8}, {"tMs": 14191, "midi": 41.8}, {"tMs": 14214, "midi": 40.8}, {"tMs": 14237, "midi": 40.8}, {"tMs": 14260, "midi": 40.8}, {"tMs": 14283, "midi": 40.8}, {"tMs": 14306, "midi": 40.8}, {"tMs": 14329, "midi": 40.8}, {"tMs": 14352, "midi": 40.8}, {"tMs": 14375, "midi": 40.8}, {"tMs": 14398, "midi": 40.8}, {"tMs": 14421, "midi": 40.8}, {"tMs": 14444, "midi": 40.8}, {"tMs": 14467, "midi": 40.8}, {"tMs": 14490, "midi": 40.8}, {"tMs": 14513, "midi": 40.8}, {"tMs": 14536, "midi": 40.8}, {"tMs": 14559, "midi": 40.8}, {"tMs": 14582, "midi": 40.9}, {"tMs": 14605, "midi": 40.9}, {"tMs": 14766, "midi": 40.2}, {"tMs": 14789, "midi": 40.5}, {"tMs": 14812, "midi": 40.8}, {"tMs": 14835, "midi": 40.1}, {"tMs": 14858, "midi": 40.1}, {"tMs": 14881, "midi": 40.8}, {"tMs": 14904, "midi": 40.8}, {"tMs": 14927, "midi": 40.5}, {"tMs": 14950, "midi": 40.8}, {"tMs": 14973, "midi": 40.7}, {"tMs": 14996, "midi": 44.7}, {"tMs": 15019, "midi": 44.7}, {"tMs": 15042, "midi": 45.4}, {"tMs": 15065, "midi": 45.4}, {"tMs": 15088, "midi": 45.7}, {"tMs": 15111, "midi": 45.8}, {"tMs": 15134, "midi": 46.4}, {"tMs": 15157, "midi": 46.4}, {"tMs": 15180, "midi": 46.1}, {"tMs": 15203, "midi": 46.1}, {"tMs": 15226, "midi": 46.1}, {"tMs": 15249, "midi": 46.1}, {"tMs": 15272, "midi": 45.9}, {"tMs": 15295, "midi": 46.2}, {"tMs": 15318, "midi": 46.6}, {"tMs": 15341, "midi": 46.8}, {"tMs": 15364, "midi": 46.7}, {"tMs": 15387, "midi": 46.7}, {"tMs": 15410, "midi": 46.8}, {"tMs": 15433, "midi": 46.9}, {"tMs": 15479, "midi": 40.2}, {"tMs": 15502, "midi": 40.2}, {"tMs": 15525, "midi": 40.2}, {"tMs": 15548, "midi": 40.2}, {"tMs": 15571, "midi": 40.2}, {"tMs": 15594, "midi": 39.7}, {"tMs": 15617, "midi": 39.9}, {"tMs": 15640, "midi": 39.7}, {"tMs": 15663, "midi": 39.7}, {"tMs": 15686, "midi": 39.7}, {"tMs": 15709, "midi": 39.7}, {"tMs": 15732, "midi": 39.7}, {"tMs": 15755, "midi": 40.0}, {"tMs": 15778, "midi": 40.7}, {"tMs": 15801, "midi": 40.8}, {"tMs": 15824, "midi": 40.7}, {"tMs": 15847, "midi": 40.7}, {"tMs": 15870, "midi": 40.7}, {"tMs": 15893, "midi": 36.8}, {"tMs": 16721, "midi": 36.3}, {"tMs": 16744, "midi": 40.8}, {"tMs": 16767, "midi": 40.8}, {"tMs": 16790, "midi": 40.8}, {"tMs": 16813, "midi": 40.8}, {"tMs": 16836, "midi": 40.8}, {"tMs": 16859, "midi": 40.8}, {"tMs": 16882, "midi": 40.8}, {"tMs": 16905, "midi": 40.8}, {"tMs": 16928, "midi": 40.8}, {"tMs": 16951, "midi": 40.8}, {"tMs": 16974, "midi": 40.8}, {"tMs": 16997, "midi": 40.8}, {"tMs": 17020, "midi": 40.8}, {"tMs": 17043, "midi": 40.8}, {"tMs": 17066, "midi": 40.8}, {"tMs": 17089, "midi": 40.8}, {"tMs": 17112, "midi": 40.8}, {"tMs": 17135, "midi": 40.9}, {"tMs": 17158, "midi": 40.9}, {"tMs": 17526, "midi": 47.6}, {"tMs": 17549, "midi": 46.9}, {"tMs": 17572, "midi": 46.6}, {"tMs": 17595, "midi": 45.8}, {"tMs": 17618, "midi": 45.7}, {"tMs": 17641, "midi": 45.1}, {"tMs": 17664, "midi": 45.0}, {"tMs": 17687, "midi": 45.4}, {"tMs": 17710, "midi": 45.8}, {"tMs": 17733, "midi": 47.6}, {"tMs": 17756, "midi": 47.6}, {"tMs": 17779, "midi": 47.2}, {"tMs": 17802, "midi": 47.3}, {"tMs": 17825, "midi": 47.2}, {"tMs": 17848, "midi": 47.2}, {"tMs": 17871, "midi": 46.8}, {"tMs": 17894, "midi": 46.9}, {"tMs": 17917, "midi": 46.9}, {"tMs": 17940, "midi": 48.0}, {"tMs": 18147, "midi": 66.5}, {"tMs": 18170, "midi": 66.8}, {"tMs": 18193, "midi": 66.9}, {"tMs": 18216, "midi": 67.0}, {"tMs": 18239, "midi": 67.1}, {"tMs": 18262, "midi": 67.3}, {"tMs": 18285, "midi": 67.4}, {"tMs": 18308, "midi": 67.5}, {"tMs": 18331, "midi": 67.6}, {"tMs": 18354, "midi": 67.8}, {"tMs": 18377, "midi": 68.1}, {"tMs": 18400, "midi": 68.6}, {"tMs": 18423, "midi": 68.9}, {"tMs": 18446, "midi": 69.0}, {"tMs": 18469, "midi": 69.3}, {"tMs": 18492, "midi": 69.7}, {"tMs": 18515, "midi": 69.9}, {"tMs": 18538, "midi": 70.0}, {"tMs": 18561, "midi": 70.0}, {"tMs": 18584, "midi": 70.1}, {"tMs": 18607, "midi": 70.1}, {"tMs": 18630, "midi": 70.3}, {"tMs": 18653, "midi": 70.6}, {"tMs": 18676, "midi": 70.7}, {"tMs": 18699, "midi": 71.1}, {"tMs": 18722, "midi": 71.7}, {"tMs": 18745, "midi": 72.0}, {"tMs": 18768, "midi": 72.2}, {"tMs": 18791, "midi": 72.5}, {"tMs": 18814, "midi": 72.7}, {"tMs": 18837, "midi": 72.9}, {"tMs": 18860, "midi": 73.3}, {"tMs": 18883, "midi": 73.5}, {"tMs": 18906, "midi": 73.7}, {"tMs": 18929, "midi": 73.8}, {"tMs": 18952, "midi": 73.9}, {"tMs": 18975, "midi": 74.1}, {"tMs": 18998, "midi": 74.3}, {"tMs": 19021, "midi": 74.5}, {"tMs": 19044, "midi": 74.8}, {"tMs": 19067, "midi": 74.9}, {"tMs": 19090, "midi": 75.1}, {"tMs": 19113, "midi": 75.4}, {"tMs": 19136, "midi": 75.7}, {"tMs": 19159, "midi": 75.9}, {"tMs": 19182, "midi": 76.2}, {"tMs": 19205, "midi": 76.4}, {"tMs": 19228, "midi": 76.5}, {"tMs": 19251, "midi": 76.8}, {"tMs": 19274, "midi": 76.9}, {"tMs": 19297, "midi": 76.9}, {"tMs": 19320, "midi": 77.0}, {"tMs": 19343, "midi": 77.2}, {"tMs": 19435, "midi": 71.8}, {"tMs": 19458, "midi": 67.0}, {"tMs": 19481, "midi": 67.1}, {"tMs": 19504, "midi": 67.1}, {"tMs": 19527, "midi": 67.2}, {"tMs": 19550, "midi": 67.2}, {"tMs": 19573, "midi": 67.3}, {"tMs": 19596, "midi": 67.5}, {"tMs": 21919, "midi": 37.6}, {"tMs": 21942, "midi": 36.9}, {"tMs": 21965, "midi": 36.9}, {"tMs": 21988, "midi": 36.9}, {"tMs": 22011, "midi": 36.0}, {"tMs": 22034, "midi": 36.0}, {"tMs": 22057, "midi": 36.0}, {"tMs": 22080, "midi": 36.1}, {"tMs": 22103, "midi": 36.1}, {"tMs": 22126, "midi": 36.3}, {"tMs": 22149, "midi": 36.4}, {"tMs": 22172, "midi": 36.4}, {"tMs": 22195, "midi": 36.9}, {"tMs": 23874, "midi": 36.0}, {"tMs": 23897, "midi": 36.0}, {"tMs": 23920, "midi": 36.0}, {"tMs": 23943, "midi": 36.0}, {"tMs": 23966, "midi": 36.0}, {"tMs": 23989, "midi": 36.2}, {"tMs": 24012, "midi": 36.0}, {"tMs": 25967, "midi": 36.0}, {"tMs": 25990, "midi": 36.0}, {"tMs": 26013, "midi": 36.2}, {"tMs": 26036, "midi": 36.2}, {"tMs": 26059, "midi": 36.0}, {"tMs": 26082, "midi": 36.0}, {"tMs": 26105, "midi": 36.0}, {"tMs": 26772, "midi": 36.0}, {"tMs": 26795, "midi": 36.0}, {"tMs": 26818, "midi": 36.0}, {"tMs": 26841, "midi": 36.0}, {"tMs": 26864, "midi": 36.0}, {"tMs": 26887, "midi": 36.4}, {"tMs": 26910, "midi": 36.0}, {"tMs": 27807, "midi": 45.0}, {"tMs": 27830, "midi": 45.0}, {"tMs": 27853, "midi": 45.0}, {"tMs": 27876, "midi": 45.0}, {"tMs": 27899, "midi": 45.0}, {"tMs": 27922, "midi": 45.0}, {"tMs": 27945, "midi": 46.6}, {"tMs": 27968, "midi": 46.6}, {"tMs": 27991, "midi": 46.6}, {"tMs": 28014, "midi": 47.2}, {"tMs": 28037, "midi": 47.2}, {"tMs": 28060, "midi": 47.2}, {"tMs": 28083, "midi": 46.5}, {"tMs": 28106, "midi": 47.2}, {"tMs": 28129, "midi": 47.2}, {"tMs": 28152, "midi": 47.2}, {"tMs": 28175, "midi": 46.5}, {"tMs": 28198, "midi": 46.4}, {"tMs": 28221, "midi": 46.4}, {"tMs": 28336, "midi": 39.8}, {"tMs": 28359, "midi": 39.8}, {"tMs": 28382, "midi": 39.8}, {"tMs": 28405, "midi": 39.6}, {"tMs": 28428, "midi": 39.6}, {"tMs": 28451, "midi": 39.5}, {"tMs": 28474, "midi": 38.7}, {"tMs": 28497, "midi": 38.6}, {"tMs": 28520, "midi": 36.0}, {"tMs": 28543, "midi": 36.0}, {"tMs": 28566, "midi": 36.4}, {"tMs": 28589, "midi": 36.4}, {"tMs": 28612, "midi": 36.4}, {"tMs": 28635, "midi": 37.2}, {"tMs": 28658, "midi": 36.6}, {"tMs": 28681, "midi": 36.6}, {"tMs": 28704, "midi": 36.6}, {"tMs": 28727, "midi": 36.6}, {"tMs": 28750, "midi": 36.6}, {"tMs": 28773, "midi": 36.5}, {"tMs": 28796, "midi": 36.0}, {"tMs": 30567, "midi": 36.0}, {"tMs": 30590, "midi": 36.0}, {"tMs": 30613, "midi": 36.0}, {"tMs": 30636, "midi": 36.0}, {"tMs": 30659, "midi": 36.0}, {"tMs": 30682, "midi": 39.7}, {"tMs": 30705, "midi": 42.8}, {"tMs": 30728, "midi": 42.0}, {"tMs": 30751, "midi": 40.2}, {"tMs": 30774, "midi": 40.2}, {"tMs": 30797, "midi": 40.2}, {"tMs": 30820, "midi": 40.2}, {"tMs": 30843, "midi": 40.2}, {"tMs": 30866, "midi": 40.2}, {"tMs": 30889, "midi": 40.2}, {"tMs": 30912, "midi": 40.2}, {"tMs": 30935, "midi": 39.7}, {"tMs": 30958, "midi": 39.7}, {"tMs": 30981, "midi": 39.7}, {"tMs": 31004, "midi": 36.0}, {"tMs": 31027, "midi": 36.0}, {"tMs": 31050, "midi": 36.0}, {"tMs": 31073, "midi": 36.0}, {"tMs": 31096, "midi": 36.0}, {"tMs": 31119, "midi": 38.3}, {"tMs": 31142, "midi": 40.8}, {"tMs": 31165, "midi": 40.8}, {"tMs": 31188, "midi": 43.6}, {"tMs": 31211, "midi": 43.7}, {"tMs": 31234, "midi": 40.2}, {"tMs": 31257, "midi": 40.2}, {"tMs": 31280, "midi": 40.2}, {"tMs": 31303, "midi": 40.2}, {"tMs": 31326, "midi": 40.2}, {"tMs": 31349, "midi": 40.2}, {"tMs": 31372, "midi": 40.2}, {"tMs": 31395, "midi": 39.7}, {"tMs": 31418, "midi": 39.9}, {"tMs": 31441, "midi": 39.9}, {"tMs": 31464, "midi": 39.9}, {"tMs": 31487, "midi": 37.4}, {"tMs": 31717, "midi": 47.2}, {"tMs": 31740, "midi": 47.2}, {"tMs": 31763, "midi": 47.2}, {"tMs": 31786, "midi": 47.2}, {"tMs": 31809, "midi": 47.2}, {"tMs": 31832, "midi": 47.2}, {"tMs": 31855, "midi": 47.2}, {"tMs": 31878, "midi": 47.2}, {"tMs": 31901, "midi": 47.2}, {"tMs": 31924, "midi": 45.8}, {"tMs": 31947, "midi": 45.8}, {"tMs": 31970, "midi": 45.7}, {"tMs": 31993, "midi": 45.7}, {"tMs": 32039, "midi": 41.3}, {"tMs": 32062, "midi": 41.3}, {"tMs": 32085, "midi": 41.3}, {"tMs": 32108, "midi": 41.3}, {"tMs": 32131, "midi": 41.3}, {"tMs": 32154, "midi": 41.3}, {"tMs": 32177, "midi": 41.3}, {"tMs": 32200, "midi": 40.8}, {"tMs": 32223, "midi": 40.8}, {"tMs": 32246, "midi": 40.8}, {"tMs": 32269, "midi": 40.8}, {"tMs": 32292, "midi": 40.8}, {"tMs": 32315, "midi": 40.8}, {"tMs": 32338, "midi": 40.8}, {"tMs": 32361, "midi": 40.8}, {"tMs": 32384, "midi": 40.8}, {"tMs": 32407, "midi": 40.8}, {"tMs": 32430, "midi": 40.8}, {"tMs": 32453, "midi": 40.8}, {"tMs": 32476, "midi": 37.1}, {"tMs": 32798, "midi": 41.4}, {"tMs": 32821, "midi": 41.3}, {"tMs": 32844, "midi": 45.0}, {"tMs": 32867, "midi": 45.0}, {"tMs": 32890, "midi": 45.0}, {"tMs": 32913, "midi": 45.0}, {"tMs": 32936, "midi": 45.0}, {"tMs": 32959, "midi": 45.0}, {"tMs": 32982, "midi": 45.0}, {"tMs": 33005, "midi": 45.8}, {"tMs": 33028, "midi": 47.2}, {"tMs": 33051, "midi": 47.2}, {"tMs": 33074, "midi": 47.2}, {"tMs": 33097, "midi": 47.2}, {"tMs": 33120, "midi": 47.2}, {"tMs": 33143, "midi": 47.2}, {"tMs": 33166, "midi": 46.5}, {"tMs": 33189, "midi": 46.5}, {"tMs": 33212, "midi": 46.5}, {"tMs": 33235, "midi": 46.5}, {"tMs": 33258, "midi": 46.5}, {"tMs": 33281, "midi": 46.5}, {"tMs": 33327, "midi": 40.2}, {"tMs": 33350, "midi": 40.2}, {"tMs": 33373, "midi": 40.2}, {"tMs": 33396, "midi": 40.2}, {"tMs": 33419, "midi": 40.2}, {"tMs": 33442, "midi": 40.2}, {"tMs": 33465, "midi": 39.7}, {"tMs": 33488, "midi": 39.7}, {"tMs": 33511, "midi": 39.7}, {"tMs": 33534, "midi": 39.2}, {"tMs": 33557, "midi": 39.7}, {"tMs": 33580, "midi": 39.7}, {"tMs": 33603, "midi": 39.7}, {"tMs": 33626, "midi": 39.7}, {"tMs": 33649, "midi": 38.3}, {"tMs": 33672, "midi": 40.3}, {"tMs": 33695, "midi": 38.3}, {"tMs": 33718, "midi": 38.3}, {"tMs": 33741, "midi": 40.8}, {"tMs": 33764, "midi": 41.2}, {"tMs": 33787, "midi": 40.2}, {"tMs": 33810, "midi": 40.2}, {"tMs": 33833, "midi": 40.2}, {"tMs": 33856, "midi": 40.2}, {"tMs": 33879, "midi": 40.2}, {"tMs": 33902, "midi": 40.2}, {"tMs": 33925, "midi": 39.7}, {"tMs": 33948, "midi": 39.7}, {"tMs": 33971, "midi": 43.3}, {"tMs": 33994, "midi": 43.4}, {"tMs": 34017, "midi": 43.4}, {"tMs": 34040, "midi": 43.4}, {"tMs": 34063, "midi": 43.4}, {"tMs": 34086, "midi": 43.5}, {"tMs": 34201, "midi": 48.9}, {"tMs": 34224, "midi": 48.9}, {"tMs": 34247, "midi": 48.9}, {"tMs": 34270, "midi": 47.2}, {"tMs": 34293, "midi": 47.2}, {"tMs": 34316, "midi": 47.2}, {"tMs": 34339, "midi": 47.2}, {"tMs": 34362, "midi": 47.2}, {"tMs": 34385, "midi": 47.2}, {"tMs": 34408, "midi": 47.2}, {"tMs": 34431, "midi": 47.2}, {"tMs": 34454, "midi": 45.7}, {"tMs": 34477, "midi": 45.7}, {"tMs": 34500, "midi": 45.7}, {"tMs": 34523, "midi": 45.7}, {"tMs": 34546, "midi": 46.5}, {"tMs": 34592, "midi": 41.3}, {"tMs": 34615, "midi": 41.3}, {"tMs": 34638, "midi": 41.3}, {"tMs": 34661, "midi": 41.3}, {"tMs": 34684, "midi": 41.3}, {"tMs": 34707, "midi": 41.3}, {"tMs": 34730, "midi": 41.3}, {"tMs": 34753, "midi": 40.8}, {"tMs": 34776, "midi": 40.8}, {"tMs": 34799, "midi": 40.8}, {"tMs": 34822, "midi": 40.8}, {"tMs": 34845, "midi": 40.8}, {"tMs": 34868, "midi": 40.8}, {"tMs": 34891, "midi": 40.8}, {"tMs": 34914, "midi": 40.8}, {"tMs": 34937, "midi": 40.8}, {"tMs": 34960, "midi": 40.8}, {"tMs": 34983, "midi": 40.8}, {"tMs": 35006, "midi": 40.8}, {"tMs": 35029, "midi": 40.8}, {"tMs": 35075, "midi": 41.3}, {"tMs": 35098, "midi": 41.3}, {"tMs": 35121, "midi": 41.3}, {"tMs": 35144, "midi": 40.8}, {"tMs": 35167, "midi": 40.8}, {"tMs": 35190, "midi": 40.8}, {"tMs": 35213, "midi": 40.8}, {"tMs": 35236, "midi": 40.8}, {"tMs": 35259, "midi": 41.8}, {"tMs": 35282, "midi": 41.8}, {"tMs": 35328, "midi": 41.8}, {"tMs": 35351, "midi": 40.9}, {"tMs": 35374, "midi": 40.8}, {"tMs": 35397, "midi": 45.0}, {"tMs": 35420, "midi": 45.0}, {"tMs": 35443, "midi": 45.0}, {"tMs": 35466, "midi": 45.0}, {"tMs": 35489, "midi": 45.0}, {"tMs": 35512, "midi": 45.0}, {"tMs": 35535, "midi": 45.0}, {"tMs": 35558, "midi": 47.2}, {"tMs": 35581, "midi": 47.2}, {"tMs": 35604, "midi": 47.2}, {"tMs": 35627, "midi": 47.2}, {"tMs": 35650, "midi": 47.2}, {"tMs": 35673, "midi": 47.2}, {"tMs": 35696, "midi": 47.2}, {"tMs": 35719, "midi": 47.2}, {"tMs": 35742, "midi": 47.2}, {"tMs": 35765, "midi": 47.2}, {"tMs": 35788, "midi": 47.2}, {"tMs": 35811, "midi": 47.2}, {"tMs": 35834, "midi": 47.2}, {"tMs": 35880, "midi": 40.2}, {"tMs": 35903, "midi": 40.2}, {"tMs": 35926, "midi": 40.2}, {"tMs": 35949, "midi": 40.2}, {"tMs": 35972, "midi": 40.2}, {"tMs": 35995, "midi": 40.2}, {"tMs": 36018, "midi": 40.2}, {"tMs": 36041, "midi": 39.7}, {"tMs": 36064, "midi": 39.7}, {"tMs": 36087, "midi": 40.2}, {"tMs": 36110, "midi": 40.2}, {"tMs": 36133, "midi": 40.2}, {"tMs": 36156, "midi": 38.7}, {"tMs": 36179, "midi": 38.7}, {"tMs": 36202, "midi": 38.7}, {"tMs": 36225, "midi": 38.7}, {"tMs": 36248, "midi": 38.7}, {"tMs": 36639, "midi": 47.4}, {"tMs": 36662, "midi": 48.9}, {"tMs": 36685, "midi": 48.1}, {"tMs": 36708, "midi": 48.0}, {"tMs": 36731, "midi": 48.0}, {"tMs": 36754, "midi": 48.0}, {"tMs": 36777, "midi": 48.9}, {"tMs": 36800, "midi": 48.0}, {"tMs": 36823, "midi": 47.2}, {"tMs": 36846, "midi": 47.2}, {"tMs": 36869, "midi": 47.2}, {"tMs": 36892, "midi": 47.2}, {"tMs": 36915, "midi": 47.2}, {"tMs": 36938, "midi": 47.2}, {"tMs": 36961, "midi": 47.2}, {"tMs": 36984, "midi": 47.2}, {"tMs": 37007, "midi": 47.2}, {"tMs": 37030, "midi": 45.8}, {"tMs": 37053, "midi": 45.8}, {"tMs": 37076, "midi": 45.8}, {"tMs": 37099, "midi": 45.8}, {"tMs": 37122, "midi": 45.7}, {"tMs": 37145, "midi": 40.8}, {"tMs": 37168, "midi": 40.8}, {"tMs": 37191, "midi": 41.3}, {"tMs": 37214, "midi": 41.3}, {"tMs": 37237, "midi": 41.3}, {"tMs": 37260, "midi": 41.3}, {"tMs": 37283, "midi": 41.3}, {"tMs": 37306, "midi": 40.8}, {"tMs": 37329, "midi": 40.8}, {"tMs": 37352, "midi": 40.8}, {"tMs": 37375, "midi": 40.8}, {"tMs": 37398, "midi": 40.8}, {"tMs": 37421, "midi": 41.3}, {"tMs": 37444, "midi": 41.3}, {"tMs": 37467, "midi": 41.3}, {"tMs": 37490, "midi": 41.3}, {"tMs": 37513, "midi": 41.3}, {"tMs": 37536, "midi": 41.3}, {"tMs": 37559, "midi": 41.3}, {"tMs": 37950, "midi": 45.0}, {"tMs": 37973, "midi": 45.0}, {"tMs": 37996, "midi": 45.0}, {"tMs": 38019, "midi": 45.0}, {"tMs": 38042, "midi": 45.0}, {"tMs": 38065, "midi": 45.0}, {"tMs": 38088, "midi": 45.0}, {"tMs": 38111, "midi": 47.2}, {"tMs": 38134, "midi": 47.2}, {"tMs": 38157, "midi": 47.2}, {"tMs": 38180, "midi": 47.2}, {"tMs": 38203, "midi": 47.2}, {"tMs": 38226, "midi": 47.2}, {"tMs": 38249, "midi": 47.2}, {"tMs": 38272, "midi": 47.2}, {"tMs": 38295, "midi": 47.2}, {"tMs": 38318, "midi": 47.2}, {"tMs": 38341, "midi": 47.2}, {"tMs": 38364, "midi": 47.2}, {"tMs": 38387, "midi": 47.2}, {"tMs": 38410, "midi": 43.0}, {"tMs": 38456, "midi": 40.2}, {"tMs": 38479, "midi": 40.2}, {"tMs": 38502, "midi": 40.2}, {"tMs": 38525, "midi": 40.2}, {"tMs": 38548, "midi": 40.2}, {"tMs": 38571, "midi": 40.2}, {"tMs": 38594, "midi": 39.7}, {"tMs": 38617, "midi": 39.7}, {"tMs": 38640, "midi": 38.7}, {"tMs": 38663, "midi": 36.9}, {"tMs": 38686, "midi": 36.0}, {"tMs": 38709, "midi": 36.0}, {"tMs": 38732, "midi": 36.0}, {"tMs": 38755, "midi": 36.0}, {"tMs": 38778, "midi": 36.0}, {"tMs": 39169, "midi": 38.9}, {"tMs": 39192, "midi": 39.3}, {"tMs": 39215, "midi": 38.9}, {"tMs": 39238, "midi": 38.9}, {"tMs": 39261, "midi": 38.9}, {"tMs": 39284, "midi": 38.9}, {"tMs": 39307, "midi": 38.9}, {"tMs": 39330, "midi": 38.9}, {"tMs": 39353, "midi": 37.0}, {"tMs": 39376, "midi": 36.0}, {"tMs": 39399, "midi": 36.0}, {"tMs": 39422, "midi": 36.0}, {"tMs": 39445, "midi": 36.1}, {"tMs": 43056, "midi": 45.0}, {"tMs": 43079, "midi": 45.0}, {"tMs": 43102, "midi": 45.0}, {"tMs": 43125, "midi": 45.0}, {"tMs": 43148, "midi": 45.0}, {"tMs": 43171, "midi": 45.0}, {"tMs": 43194, "midi": 45.0}, {"tMs": 43217, "midi": 47.2}, {"tMs": 43240, "midi": 47.2}, {"tMs": 43263, "midi": 47.2}, {"tMs": 43286, "midi": 47.2}, {"tMs": 43309, "midi": 47.2}, {"tMs": 43332, "midi": 47.2}, {"tMs": 43355, "midi": 47.2}, {"tMs": 43378, "midi": 47.2}, {"tMs": 43401, "midi": 46.5}, {"tMs": 43424, "midi": 46.5}, {"tMs": 43447, "midi": 46.5}, {"tMs": 43470, "midi": 46.5}, {"tMs": 43493, "midi": 46.5}, {"tMs": 45540, "midi": 41.5}, {"tMs": 45563, "midi": 41.6}, {"tMs": 45586, "midi": 40.8}, {"tMs": 45609, "midi": 40.8}, {"tMs": 45632, "midi": 45.0}, {"tMs": 45655, "midi": 45.0}, {"tMs": 45678, "midi": 45.0}, {"tMs": 45701, "midi": 45.0}, {"tMs": 45724, "midi": 45.0}, {"tMs": 45747, "midi": 45.0}, {"tMs": 45770, "midi": 45.1}, {"tMs": 45793, "midi": 47.2}, {"tMs": 45816, "midi": 47.2}, {"tMs": 45839, "midi": 47.2}, {"tMs": 45862, "midi": 47.2}, {"tMs": 45885, "midi": 47.2}, {"tMs": 45908, "midi": 47.2}, {"tMs": 45931, "midi": 47.2}, {"tMs": 45954, "midi": 47.2}, {"tMs": 45977, "midi": 47.2}, {"tMs": 46000, "midi": 47.2}, {"tMs": 46023, "midi": 45.7}, {"tMs": 48093, "midi": 39.9}, {"tMs": 48116, "midi": 39.9}, {"tMs": 48139, "midi": 42.4}, {"tMs": 48162, "midi": 45.0}, {"tMs": 48185, "midi": 45.0}, {"tMs": 48208, "midi": 45.0}, {"tMs": 48231, "midi": 45.0}, {"tMs": 48254, "midi": 45.0}, {"tMs": 48277, "midi": 45.0}, {"tMs": 48300, "midi": 45.0}, {"tMs": 48323, "midi": 45.0}, {"tMs": 48346, "midi": 47.3}, {"tMs": 48369, "midi": 47.2}, {"tMs": 48392, "midi": 47.2}, {"tMs": 48415, "midi": 47.2}, {"tMs": 48438, "midi": 47.2}, {"tMs": 48461, "midi": 47.2}, {"tMs": 48484, "midi": 47.2}, {"tMs": 48507, "midi": 47.2}, {"tMs": 48530, "midi": 47.2}, {"tMs": 48553, "midi": 47.2}, {"tMs": 48576, "midi": 45.7}, {"tMs": 48599, "midi": 45.7}, {"tMs": 54234, "midi": 40.2}, {"tMs": 54257, "midi": 40.2}, {"tMs": 54280, "midi": 40.2}, {"tMs": 54303, "midi": 40.2}, {"tMs": 54326, "midi": 40.2}, {"tMs": 54349, "midi": 40.2}, {"tMs": 54372, "midi": 40.3}, {"tMs": 54395, "midi": 40.3}, {"tMs": 54418, "midi": 39.8}, {"tMs": 54441, "midi": 36.4}, {"tMs": 54464, "midi": 36.1}, {"tMs": 54487, "midi": 36.1}, {"tMs": 58052, "midi": 40.8}, {"tMs": 58075, "midi": 40.8}, {"tMs": 58098, "midi": 40.8}, {"tMs": 58121, "midi": 40.8}, {"tMs": 58144, "midi": 40.8}, {"tMs": 58167, "midi": 40.8}, {"tMs": 58190, "midi": 40.8}, {"tMs": 58213, "midi": 40.2}, {"tMs": 58236, "midi": 41.8}, {"tMs": 58259, "midi": 41.8}, {"tMs": 58282, "midi": 41.8}, {"tMs": 58305, "midi": 40.6}, {"tMs": 58328, "midi": 40.8}, {"tMs": 58351, "midi": 40.8}, {"tMs": 58374, "midi": 40.7}, {"tMs": 58397, "midi": 45.0}, {"tMs": 58420, "midi": 45.0}, {"tMs": 58443, "midi": 45.0}, {"tMs": 58466, "midi": 45.0}, {"tMs": 58489, "midi": 45.0}, {"tMs": 58512, "midi": 44.4}, {"tMs": 58535, "midi": 45.0}, {"tMs": 58558, "midi": 45.0}, {"tMs": 58627, "midi": 46.5}, {"tMs": 58650, "midi": 46.5}, {"tMs": 58673, "midi": 46.5}, {"tMs": 58696, "midi": 46.5}, {"tMs": 58719, "midi": 46.5}, {"tMs": 58742, "midi": 46.5}, {"tMs": 58765, "midi": 47.2}, {"tMs": 58788, "midi": 47.2}, {"tMs": 58811, "midi": 47.2}, {"tMs": 58857, "midi": 40.7}, {"tMs": 58880, "midi": 40.7}, {"tMs": 58903, "midi": 40.3}, {"tMs": 58926, "midi": 40.3}, {"tMs": 58949, "midi": 40.2}, {"tMs": 58972, "midi": 39.7}, {"tMs": 58995, "midi": 39.7}, {"tMs": 59018, "midi": 39.7}, {"tMs": 59041, "midi": 39.7}, {"tMs": 59064, "midi": 39.7}, {"tMs": 59087, "midi": 39.7}, {"tMs": 59110, "midi": 39.7}, {"tMs": 59133, "midi": 39.7}, {"tMs": 59156, "midi": 40.2}, {"tMs": 59179, "midi": 39.6}, {"tMs": 59202, "midi": 39.6}, {"tMs": 59225, "midi": 39.6}, {"tMs": 59248, "midi": 39.6}, {"tMs": 59271, "midi": 39.6}], "extractor": "librosa.pyin", "separated": true, "durationMs": 60000}