{"synced": "[00:06.97] どこから春が巡り来るのか\n[00:10.87] 知らず知らず大人になった\n[00:15.26] 見上げた先には燕が飛んでた\n[00:19.77] 気のない顔で\n[00:22.61] もしもわたしに翼があれば\n[00:26.67] 願う度に悲しみに暮れた\n[00:30.83] さよなら 100年先でまた会いましょう\n[00:35.30] 心配しないで\n[00:39.07] いつの間にか 花が落ちた\n[00:43.05] 誰かがわたしに嘘をついた\n[00:47.02] 土砂降りでも構わず飛んでく\n[00:51.01] その力が欲しかった\n[00:56.85] 誰かと恋に落ちて また砕けて やがて離れ離れ\n[01:04.92] 口の中はたと血が滲んで 空に唾を吐く\n[01:12.57] 瞬け 羽を広げ 気儘に飛べ どこまでもゆけ\n[01:20.52] 100年先も憶えてるかな 知らねえけれど\n[01:26.56] さよーならまたいつか！\n[01:30.82] \n[01:39.28] しぐるるやしぐるる町へ歩み入る\n[01:44.49] そこかしこで袖触れる\n[01:47.87] 見上げた先には何も居なかった\n[01:52.00] ああ居なかった\n[01:55.83] したり顔で 触らないで\n[01:59.81] 背中を殴りつける的外れ\n[02:03.81] 人が宣う地獄の先にこそ\n[02:08.29] わたしは春を見る\n[02:13.61] 誰かを愛したくて でも痛くて いつしか雨霰\n[02:21.66] 繋がれてた縄を握りしめて しかと噛みちぎる\n[02:29.25] 貫け 狙い定め 蓋し虎へ どこまでもゆけ\n[02:37.45] 100年先のあなたに会いたい 消え失せるなよ\n[02:43.35] さよーならまたいつか！\n[02:46.48] 今恋に落ちて また砕けて 離れ離れ\n[02:53.13] 口の中はたと血が滲んで 空に唾を吐く\n[03:02.13] 今羽を広げ 気儘に飛べ どこまでもゆけ\n[03:08.93] 生まれた日からわたしでいたんだ 知らなかっただろ\n[03:14.79] さよーならまたいつか！\n[03:17.22] ", "plain": "どこから春が巡り来るのか\n知らず知らず大人になった\n見上げた先には燕が飛んでた\n気のない顔で\n\nもしもわたしに翼があれば\n願う度に悲しみに暮れた\nさよなら 100年先でまた会いましょう\n心配しないで\n\nいつの間にか 花が落ちた\n誰かがわたしに嘘をついた\n土砂降りでも構わず飛んでく\nその力が欲しかった\n\n誰かと恋に落ちて また砕けて やがて離れ離れ\n口の中はたと血が滲んで 空に唾を吐く\n瞬け 羽を広げ 気儘に飛べ どこまでもゆけ\n100年先も憶えてるかな 知らねえけれど\nさよーならまたいつか！\n\nしぐるるやしぐるる町へ歩み入る\nそこかしこで袖触れる\n見上げた先には何も居なかった\nああ居なかった\n\nしたり顔で 触らないで\n背中を殴りつける的外れ\n人が宣う地獄の先にこそ\nわたしは春を見る\n\n誰かを愛したくて でも痛くて いつしか雨霰\n繋がれてた縄を握りしめて しかと噛みちぎる\n貫け 狙い定め 蓋し虎へ どこまでもゆけ\n100年先のあなたに会いたい 消え失せるなよ\nさよーならまたいつか！\n\n今恋に落ちて また砕けて 離れ離れ\n口の中はたと血が滲んで 空に唾を吐く\n今羽を広げ 気儘に飛べ どこまでもゆけ\n生まれた日からわたしでいたんだ 知らなかっただろ\nさよーならまたいつか！", "matched_artist": "米津玄師", "matched_track": "さよーならまたいつか！", "source": "prefetch"}