{"synced": "[00:14.26] Yeah\n[00:18.11] \n[00:27.82] I've been tryna call\n[00:30.63] I've been on my own for long enough\n[00:33.35] Maybe you can show me how to love, maybe\n[00:38.90] I'm going through withdrawals\n[00:41.81] You don't even have to do too much\n[00:44.64] You can turn me on with just a touch, baby\n[00:50.10] I look around and\n[00:51.44] Sin City's cold and empty (oh)\n[00:54.22] No one's around to judge me (oh)\n[00:56.97] I can't see clearly when you're gone\n[01:01.31] I said, ooh, I'm blinded by the lights\n[01:07.34] No, I can't sleep until I feel your touch\n[01:12.52] I said, ooh, I'm drowning in the night\n[01:18.63] Oh, when I'm like this, you're the one I trust\n[01:23.21] (Hey, hey, hey)\n[01:26.44] \n[01:35.14] I'm running out of time\n[01:37.88] 'Cause I can see the sun light up the sky\n[01:40.70] So I hit the road in overdrive, baby, oh\n[01:47.38] The city's cold and empty (oh)\n[01:50.38] No one's around to judge me (oh)\n[01:53.15] I can't see clearly when you're gone\n[01:57.54] I said, ooh, I'm blinded by the lights\n[02:03.59] No, I can't sleep until I feel your touch\n[02:08.64] I said, ooh, I'm drowning in the night\n[02:14.71] Oh, when I'm like this, you're the one I trust\n[02:20.19] I'm just walking by to let you know (by to let you know)\n[02:23.05] I can never say it on the phone (say it on the phone)\n[02:26.02] Will never let you go this time (ooh)\n[02:31.22] I said, ooh, I'm blinded by the lights\n[02:37.14] No, I can't sleep until I feel your touch\n[02:41.68] (Hey, hey, hey)\n[02:44.82] \n[02:52.44] (Hey, hey, hey)\n[02:55.82] \n[03:04.88] I said, ooh, I'm blinded by the lights\n[03:10.84] No, I can't sleep until I feel your touch\n[03:14.38] ", "plain": "Yeah\n\nI've been tryna call\nI've been on my own for long enough\nMaybe you can show me how to love, maybe\nI'm going through withdrawals\nYou don't even have to do too much\nYou can turn me on with just a touch, baby\n\nI look around and\nSin City's cold and empty (oh)\nNo one's around to judge me (oh)\nI can't see clearly when you're gone\n\nI said, ooh, I'm blinded by the lights\nNo, I can't sleep until I feel your touch\nI said, ooh, I'm drowning in the night\nOh, when I'm like this, you're the one I trust\n(Hey, hey, hey)\n\nI'm running out of time\n'Cause I can see the sun light up the sky\nSo I hit the road in overdrive, baby, oh\n\nThe city's cold and empty (oh)\nNo one's around to judge me (oh)\nI can't see clearly when you're gone\n\nI said, ooh, I'm blinded by the lights\nNo, I can't sleep until I feel your touch\nI said, ooh, I'm drowning in the night\nOh, when I'm like this, you're the one I trust\n\nI'm just walking by to let you know (by to let you know)\nI can never say it on the phone (say it on the phone)\nWill never let you go this time (ooh)\n\nI said, ooh, I'm blinded by the lights\nNo, I can't sleep until I feel your touch\n(Hey, hey, hey)\n\n(Hey, hey, hey)\n\nI said, ooh, I'm blinded by the lights\nNo, I can't sleep until I feel your touch", "matched_artist": "The Weeknd", "matched_track": "Blinding Lights", "source": "prefetch"}