{"synced": "[00:10.29] Walk in your rainbow paradise (paradise)\n[00:19.75] Strawberry lipstick state of mind (state of mind)\n[00:29.72] I get so lost inside your eyes\n[00:35.72] Would you believe it?\n[00:38.64] You don't have to say you love me\n[00:41.18] You don't have to say nothing\n[00:43.54] You don't have to say you're mine\n[00:47.88] Honey (ah)\n[00:51.84] I'd walk through fire for you\n[00:54.34] Just let me adore you\n[00:57.19] Oh honey (ah)\n[01:01.39] I'd walk through fire for you\n[01:04.05] Just let me adore you\n[01:06.04] Like it's the only thing I'll ever do\n[01:10.82] Like it's the only thing I'll ever do\n[01:15.19] \n[01:18.13] Your wonder under summer skies (summer skies)\n[01:27.76] Brown skin and lemon over ice\n[01:33.95] Would you believe it?\n[01:37.05] You don't have to say you love me\n[01:39.30] I just wanna tell you something\n[01:41.76] Lately, you've been on my mind\n[01:46.00] Honey (ah)\n[01:49.89] I'd walk through fire for you\n[01:52.56] Just let me adore you\n[01:55.38] Oh honey (ah)\n[01:59.67] I'd walk through fire for you\n[02:02.12] Just let me adore you\n[02:04.32] Like it's the only thing I'll ever do\n[02:09.18] Like it's the only thing I'll ever do\n[02:15.36] It's the only thing I'll ever do\n[02:17.74] It's the only thing I'll ever do\n[02:20.06] It's the only thing I'll ever do\n[02:22.41] It's the only thing I'll ever do\n[02:25.06] It's the only thing I'll ever do\n[02:27.49] It's the only thing I'll ever do\n[02:29.96] It's the only thing I'll ever do\n[02:32.35] It's the only thing I'll ever do\n[02:35.03] I'd walk through fire for you\n[02:38.61] \n[02:41.14] Just let me adore you\n[02:43.80] Oh honey (ah)\n[02:48.08] I'd walk through fire for you\n[02:50.64] Just let me adore you\n[02:52.79] Like it's the only thing I'll ever do (it's the only thing I'll ever do, ah)\n[02:56.83] (It's the only thing I'll ever do)\n[02:57.78] I'd walk through fire for you (it's the only thing I'll ever do)\n[03:00.41] Just let me adore you\n[03:03.36] Oh honey (it's the only thing I'll ever do, ah)\n[03:05.65] Oh honey (it's the only thing I'll ever do)\n[03:07.66] I'd walk through fire for you (it's the only thing I'll ever do)\n[03:10.12] Just let me adore you (it's the only thing I'll ever do)\n[03:12.95] Ooh, ooh\n[03:15.53] Oh honey\n[03:17.62] Ooh, ooh\n[03:19.74] Just let me adore you\n[03:21.80] Like it's the only thing I'll ever do\n[03:23.00] ", "plain": "Walk in your rainbow paradise (paradise)\nStrawberry lipstick state of mind (state of mind)\nI get so lost inside your eyes\nWould you believe it?\n\nYou don't have to say you love me\nYou don't have to say nothing\nYou don't have to say you're mine\n\nHoney (ah)\nI'd walk through fire for you\nJust let me adore you\nOh honey (ah)\nI'd walk through fire for you\nJust let me adore you\nLike it's the only thing I'll ever do\nLike it's the only thing I'll ever do\n\nYour wonder under summer skies (summer skies)\nBrown skin and lemon over ice\nWould you believe it?\n\nYou don't have to say you love me\nI just wanna tell you something\nLately, you've been on my mind\n\nHoney (ah)\nI'd walk through fire for you\nJust let me adore you\nOh honey (ah)\nI'd walk through fire for you\nJust let me adore you\nLike it's the only thing I'll ever do\nLike it's the only thing I'll ever do\n\nIt's the only thing I'll ever do\nIt's the only thing I'll ever do\nIt's the only thing I'll ever do\nIt's the only thing I'll ever do\nIt's the only thing I'll ever do\nIt's the only thing I'll ever do\nIt's the only thing I'll ever do\nIt's the only thing I'll ever do\n\nI'd walk through fire for you\nJust let me adore you\nOh honey (ah)\nI'd walk through fire for you\nJust let me adore you\nLike it's the only thing I'll ever do (it's the only thing I'll ever do, ah)\n(It's the only thing I'll ever do)\n\nI'd walk through fire for you (it's the only thing I'll ever do)\nJust let me adore you\nOh honey (it's the only thing I'll ever do, ah)\nOh honey (it's the only thing I'll ever do)\nI'd walk through fire for you (it's the only thing I'll ever do)\nJust let me adore you (it's the only thing I'll ever do)\n\nOoh, ooh\nOh honey\nOoh, ooh\nJust let me adore you\nLike it's the only thing I'll ever do", "matched_artist": "Harry Styles", "matched_track": "Adore You", "source": "prefetch"}