{"synced": "[00:08.83] I got my driver's license last week\n[00:11.95] Just like we always talked about\n[00:15.20] 'Cause you were so excited for me\n[00:18.41] To finally drive up to your house\n[00:21.64] But today, I drove through the suburbs\n[00:25.00] Crying 'cause you weren't around\n[00:28.75] \n[00:31.84] And you're probably with that blonde girl\n[00:35.12] Who always made me doubt\n[00:38.48] She's so much older than me\n[00:41.01] She's everything I'm insecure about\n[00:44.03] Yeah, today I drove through the suburbs\n[00:47.92] 'Cause how could I ever love someone else?\n[00:54.63] And I know we weren't perfect\n[00:57.21] But I've never felt this way for no one\n[01:04.45] And I just can't imagine how you could be so okay now that I'm gone\n[01:14.48] Guess you didn't mean what you wrote in that song about me\n[01:21.10] 'Cause you said forever, now I drive alone past your street\n[01:28.98] And all my friends are tired\n[01:31.68] Of hearing how much I miss you, but\n[01:35.25] I kinda feel sorry for them\n[01:37.84] 'Cause they'll never know you the way that I do\n[01:40.99] Yeah, today I drove through the suburbs\n[01:44.44] And pictured I was driving home to you\n[01:51.11] And I know we weren't perfect\n[01:54.09] But I've never felt this way for no one, oh\n[02:01.05] And I just can't imagine how you could be so okay now that I'm gone\n[02:10.72] I guess you didn't mean what you wrote in that song about me\n[02:17.92] 'Cause you said forever, now I drive alone past your street\n[02:24.54] Red lights, stop signs\n[02:28.08] I still see your face in the white cars, front yards\n[02:34.74] Can't drive past the places we used to go to\n[02:41.28] 'Cause you know I still love you, babe (ooh, ooh-ooh, ooh-ooh)\n[02:51.24] Sidewalks we crossed\n[02:54.64] I still hear your voice in the traffic\n[02:59.39] We're laughing over all the noise\n[03:03.89] God, I'm so blue, know we're through\n[03:07.85] But you know I still love you, babe (ooh, ooh-ooh, ooh-ooh)\n[03:18.14] I know we weren't perfect\n[03:20.91] But I've never felt this way for no one\n[03:27.73] And I just can't imagine how you could be so okay now that I'm gone\n[03:37.86] Guess you didn't mean what you wrote in that song about me\n[03:44.35] 'Cause you said forever, now I drive alone past your street\n[03:51.05] Yeah, you said forever, now I drive alone past your street\n[03:56.00] ", "plain": "I got my driver's license last week\nJust like we always talked about\n'Cause you were so excited for me\nTo finally drive up to your house\nBut today, I drove through the suburbs\nCrying 'cause you weren't around\n\nAnd you're probably with that blonde girl\nWho always made me doubt\nShe's so much older than me\nShe's everything I'm insecure about\nYeah, today I drove through the suburbs\n'Cause how could I ever love someone else?\n\nAnd I know we weren't perfect\nBut I've never felt this way for no one\nAnd I just can't imagine how you could be so okay now that I'm gone\nGuess you didn't mean what you wrote in that song about me\n'Cause you said forever, now I drive alone past your street\n\nAnd all my friends are tired\nOf hearing how much I miss you, but\nI kinda feel sorry for them\n'Cause they'll never know you the way that I do\nYeah, today I drove through the suburbs\nAnd pictured I was driving home to you\n\nAnd I know we weren't perfect\nBut I've never felt this way for no one, oh\nAnd I just can't imagine how you could be so okay now that I'm gone\nI guess you didn't mean what you wrote in that song about me\n'Cause you said forever, now I drive alone past your street\n\nRed lights, stop signs\nI still see your face in the white cars, front yards\nCan't drive past the places we used to go to\n'Cause you know I still love you, babe (ooh, ooh-ooh, ooh-ooh)\nSidewalks we crossed\nI still hear your voice in the traffic\nWe're laughing over all the noise\nGod, I'm so blue, know we're through\nBut you know I still love you, babe (ooh, ooh-ooh, ooh-ooh)\n\nI know we weren't perfect\nBut I've never felt this way for no one\nAnd I just can't imagine how you could be so okay now that I'm gone\nGuess you didn't mean what you wrote in that song about me\n'Cause you said forever, now I drive alone past your street\n\nYeah, you said forever, now I drive alone past your street", "matched_artist": "Olivia Rodrigo", "matched_track": "drivers license", "source": "prefetch"}